NEMO_osticket/__init__.py
NEMO_osticket/admin.py
NEMO_osticket/apps.py
NEMO_osticket/customizations.py
NEMO_osticket/exceptions.py
NEMO_osticket/forms.py
NEMO_osticket/models.py
NEMO_osticket/osticket_search.py
NEMO_osticket/routers.py
NEMO_osticket/urls.py
NEMO_osticket/templates/NEMO_osticket/snippets/osticket_create_ticket.html
NEMO_osticket/templates/NEMO_osticket/snippets/osticket_details.html
NEMO_osticket/templates/NEMO_osticket/ticket_details/ticket_details.html
NEMO_osticket/templates/NEMO_osticket/tickets/create_ticket.html
NEMO_osticket/templates/NEMO_osticket/tickets/ticket_search.html
NEMO_osticket/templates/NEMO_osticket/tool_control/osticket_past_tasks_and_comments.html
NEMO_osticket/templates/NEMO_osticket/tool_control/osticket_tab.html
NEMO_osticket/templates/NEMO_osticket/tool_control/osticket_tab_content.html
NEMO_osticket/templates/customizations/customizations_osticket.html
NEMO_osticket/tests/__init__.py
NEMO_osticket/tests/test_osticket.py
NEMO_osticket/tests/test_settings.py
NEMO_osticket/views/__init__.py
NEMO_osticket/views/osticket.py
nemo_osticket-1.7.2.dist-info/licenses/LICENSE
nemo_osticket-1.7.2.dist-info/METADATA
nemo_osticket-1.7.2.dist-info/WHEEL
nemo_osticket-1.7.2.dist-info/top_level.txt
nemo_osticket-1.7.2.dist-info/RECORD
