Metadata-Version: 2.4
Name: NEMO-osticket
Version: 1.7.2
Summary: osTicket plugin for NEMO linking tickets to a specific tool
Author-email: Atlantis Labs LLC <atlantis@atlantislabs.io>
License: MIT License
Project-URL: Homepage, https://gitlab.com/nemo-community/atlantis-labs/nemo-osticket
Project-URL: Changelog, https://gitlab.com/nemo-community/atlantis-labs/nemo-osticket/-/releases
Project-URL: Issues, https://gitlab.com/nemo-community/atlantis-labs/nemo-osticket/-/issues
Project-URL: CI, https://gitlab.com/nemo-community/atlantis-labs/nemo-osticket/-/pipelines
Keywords: NEMO
Classifier: Development Status :: 5 - Production/Stable
Classifier: Intended Audience :: Developers
Classifier: License :: OSI Approved :: MIT License
Classifier: Framework :: Django :: 4.2
Classifier: Programming Language :: Python :: 3.9
Classifier: Programming Language :: Python :: 3.10
Classifier: Programming Language :: Python :: 3.11
Classifier: Programming Language :: Python :: 3.12
Classifier: Programming Language :: Python :: 3.13
Requires-Python: >=3.8
License-File: LICENSE
Requires-Dist: django
Requires-Dist: requests
Requires-Dist: mysql-connector-python==9.0.0
Provides-Extra: nemo-ce
Requires-Dist: NEMO-CE>=6.0.0; extra == "nemo-ce"
Provides-Extra: nemo
Requires-Dist: NEMO>=6.0.0; extra == "nemo"
Provides-Extra: dev-tools
Requires-Dist: pre-commit; extra == "dev-tools"
Requires-Dist: djlint; extra == "dev-tools"
Requires-Dist: black; extra == "dev-tools"
Dynamic: license-file
